streamlit_marquee/__init__.py
streamlit_marquee/frontend/index.html
streamlit_marquee/frontend/css/index.css
streamlit_marquee/frontend/js/index.js
streamlit_marquee-0.0.7.dist-info/METADATA
streamlit_marquee-0.0.7.dist-info/WHEEL
streamlit_marquee-0.0.7.dist-info/top_level.txt
streamlit_marquee-0.0.7.dist-info/RECORD
