Metadata-Version: 2.1
Name: streamlit-marquee
Version: 0.0.7
Summary: a streamlit marquee component
Home-page: https://github.com/inspurer/streamlit-marquee
Author: buyixiao
Author-email: 2391527690xt@gmail.com
License: MIT License
Keywords: marquee,streamlit,component
Classifier: Programming Language :: Python :: 3
Classifier: License :: OSI Approved :: MIT License
Classifier: Operating System :: OS Independent
Requires-Python: >=3.6
Requires-Dist: streamlit (>=0.75)
Requires-Dist: simplejson (>=3.0)
Requires-Dist: pandas
Requires-Dist: numpy
